openfisca_japan/__init__.py
openfisca_japan/entities.py
openfisca_japan/__pycache__/__init__.cpython-311.pyc
openfisca_japan/__pycache__/entities.cpython-311.pyc
openfisca_japan/assets/市区町村級地区分.json
openfisca_japan/assets/住民税/配偶者控除額.csv
openfisca_japan/assets/住民税/配偶者控除額_老人控除対象配偶者.csv
openfisca_japan/assets/住民税/配偶者特別控除額.csv
openfisca_japan/assets/所得/配偶者控除額.csv
openfisca_japan/assets/所得/配偶者控除額_老人控除対象配偶者.csv
openfisca_japan/assets/所得/配偶者特別控除額.csv
openfisca_japan/assets/災害/支援/災害援護資金貸付限度額.csv
openfisca_japan/assets/災害/支援/被災者生活再建支援制度_加算支援金.csv
openfisca_japan/assets/災害/支援/被災者生活再建支援制度_基礎支援金.csv
openfisca_japan/assets/福祉/生活保護/期末一時扶助.csv
openfisca_japan/assets/福祉/生活保護/障害者加算.csv
openfisca_japan/assets/福祉/生活保護/住宅扶助基準額/市.csv
openfisca_japan/assets/福祉/生活保護/住宅扶助基準額/都道府県.csv
openfisca_japan/assets/福祉/生活保護/冬季加算/1区.csv
openfisca_japan/assets/福祉/生活保護/冬季加算/2区.csv
openfisca_japan/assets/福祉/生活保護/冬季加算/3区.csv
openfisca_japan/assets/福祉/生活保護/冬季加算/4区.csv
openfisca_japan/assets/福祉/生活保護/冬季加算/5区.csv
openfisca_japan/assets/福祉/生活保護/冬季加算/6区.csv
openfisca_japan/assets/福祉/生活保護/冬季加算/地域区分.json
openfisca_japan/assets/福祉/生活保護/母子世帯等に係る経過的加算/3人世帯.csv
openfisca_japan/assets/福祉/生活保護/母子世帯等に係る経過的加算/4人世帯.csv
openfisca_japan/assets/福祉/生活保護/母子世帯等に係る経過的加算/5人世帯.csv
openfisca_japan/assets/福祉/生活保護/生活扶助基準額/第1類1.csv
openfisca_japan/assets/福祉/生活保護/生活扶助基準額/第1類2.csv
openfisca_japan/assets/福祉/生活保護/生活扶助基準額/第2類1.csv
openfisca_japan/assets/福祉/生活保護/生活扶助基準額/第2類2.csv
openfisca_japan/assets/福祉/生活保護/生活扶助基準額/逓減率1.csv
openfisca_japan/assets/福祉/生活保護/生活扶助基準額/逓減率2.csv
openfisca_japan/assets/福祉/生活保護/生活扶助本体に係る経過的加算/1人世帯.csv
openfisca_japan/assets/福祉/生活保護/生活扶助本体に係る経過的加算/2人世帯.csv
openfisca_japan/assets/福祉/生活保護/生活扶助本体に係る経過的加算/3人世帯.csv
openfisca_japan/assets/福祉/生活保護/生活扶助本体に係る経過的加算/4人世帯.csv
openfisca_japan/assets/福祉/生活保護/生活扶助本体に係る経過的加算/5人世帯.csv
openfisca_japan/assets/福祉/育児/高等学校奨学給付金/公立高等学校奨学給付金額.csv
openfisca_japan/assets/福祉/育児/高等学校奨学給付金/国立高等学校奨学給付金額.csv
openfisca_japan/assets/福祉/育児/高等学校奨学給付金/私立高等学校奨学給付金額.csv
openfisca_japan-2.0.0.dist-info/licenses/LICENSE
openfisca_japan-2.0.0.dist-info/METADATA
openfisca_japan-2.0.0.dist-info/WHEEL
openfisca_japan-2.0.0.dist-info/top_level.txt
openfisca_japan-2.0.0.dist-info/RECORD
