Metadata-Version: 2.4
Name: OpenFisca-Japan
Version: 2.0.0
Summary: OpenFisca tax and benefit system for Japan
Home-page: https://github.com/project-inclusive/OpenFisca-Japan
Author: proj-inclusive
Author-email: proj.inclusive@gmail.com
License: http://www.fsf.org/licensing/licenses/agpl-3.0.html
Keywords: benefit microsimulation social tax
Classifier: Development Status :: 5 - Production/Stable
Classifier: License :: OSI Approved :: GNU Affero General Public License v3
Classifier: Operating System :: POSIX
Classifier: Programming Language :: Python
Classifier: Programming Language :: Python :: 3.9
Classifier: Programming Language :: Python :: 3.10
Classifier: Programming Language :: Python :: 3.11
Classifier: Topic :: Scientific/Engineering :: Information Analysis
License-File: LICENSE
Requires-Dist: OpenFisca-Core[web-api]<42.0.0,>=41.0.0
Provides-Extra: dev
Requires-Dist: autopep8<2.0.0,>=1.5.4; extra == "dev"
Requires-Dist: flake8<4.0.0,>=3.8.0; extra == "dev"
Requires-Dist: flake8-bugbear<22.0.0,>=20.1.0; extra == "dev"
Requires-Dist: flake8-builtins<2.0.0,>=1.5.0; extra == "dev"
Requires-Dist: flake8-coding<2.0.0,>=1.3.0; extra == "dev"
Requires-Dist: flake8-commas<3.0.0,>=2.0.0; extra == "dev"
Requires-Dist: flake8-comprehensions<4.0.0,>=3.2.0; extra == "dev"
Requires-Dist: flake8-docstrings<2.0.0,>=1.5.0; extra == "dev"
Requires-Dist: flake8-import-order<1.0.0,>=0.18.0; extra == "dev"
Requires-Dist: flake8-print<5.0.0,>=3.1.0; extra == "dev"
Requires-Dist: flake8-quotes<4.0.0,>=3.2.0; extra == "dev"
Requires-Dist: flake8-simplify<1.0.0,>=0.9.0; extra == "dev"
Requires-Dist: flake8-use-fstring<2.0.0,>=1.1.0; extra == "dev"
Requires-Dist: pylint<3.0.0,>=2.6.0; extra == "dev"
Requires-Dist: pycodestyle<3.0.0,>=2.6.0; extra == "dev"
Requires-Dist: python-dateutil>2.8.1; extra == "dev"
Requires-Dist: PyYAML==6.0; extra == "dev"
Requires-Dist: ruff==0.1.9; extra == "dev"
Dynamic: author
Dynamic: author-email
Dynamic: classifier
Dynamic: description
Dynamic: description-content-type
Dynamic: home-page
Dynamic: keywords
Dynamic: license
Dynamic: license-file
Dynamic: provides-extra
Dynamic: requires-dist
Dynamic: summary
